extr_nlp/__init__.py
extr_nlp/entities.py
extr_nlp/iterutils.py
extr_nlp/models.py
extr_nlp/regex.py
extr_nlp/relations.py
extr_nlp-0.0.2.dist-info/LICENSE
extr_nlp-0.0.2.dist-info/METADATA
extr_nlp-0.0.2.dist-info/WHEEL
extr_nlp-0.0.2.dist-info/top_level.txt
extr_nlp-0.0.2.dist-info/RECORD
